LICENSE
MANIFEST.in
README.md
README.rst
setup.py
executed.egg-info/PKG-INFO
executed.egg-info/SOURCES.txt
executed.egg-info/dependency_links.txt
executed.egg-info/namespace_packages.txt
executed.egg-info/not-zip-safe
executed.egg-info/requires.txt
executed.egg-info/top_level.txt
src/deso/execute/__init__.py
src/deso/execute/__meta__.py
src/deso/execute/execute_.py
src/deso/execute/util.py
src/deso/execute/test/__init__.py
src/deso/execute/test/testExecute.py
src/deso/execute/test/testUtil.py