Metadata-Version: 1.1
Name: executed
Version: 0.9.0.2
Summary: A package providing a process execution facility on top of the POSIX fork/exec model.
Home-page: https://github.com/d-e-s-o/execute
Author: Daniel Mueller
Author-email: deso@posteo.net
License: GPLv3
Keywords: execute fork exec pipeline spring process development
Platform: UNKNOWN
Classifier: Development Status :: 4 - Beta
Classifier: Intended Audience :: Developers
Classifier: License :: OSI Approved :: GNU General Public License v3 (GPLv3)
Classifier: Operating System :: POSIX
Classifier: Programming Language :: Python
Classifier: Programming Language :: Python :: 3
Classifier: Topic :: Software Development :: Libraries :: Python Modules
